arithmath/__init__.py
arithmath/basic.py
arithmath-1.0.0.dist-info/licenses/LICENSE
arithmath-1.0.0.dist-info/METADATA
arithmath-1.0.0.dist-info/WHEEL
arithmath-1.0.0.dist-info/top_level.txt
arithmath-1.0.0.dist-info/RECORD
