Metadata-Version: 2.4
Name: arithmath
Version: 1.0.0
Summary: A simple mathematical utilities package
Home-page: https://github.com/harrshjain/arithmath
Author: Harsh Jain
Author-email: Harsh <harshjacksn@gmail.com>
License: MIT
Project-URL: Homepage, https://github.com/harrshjain/arithmath
Project-URL: Repository, https://github.com/harrshjain/arithmath
Project-URL: Issues, https://github.com/harrshjain/arithmath/issues
Classifier: Development Status :: 3 - Alpha
Classifier: Intended Audience :: Developers
Classifier: License :: OSI Approved :: MIT License
Classifier: Operating System :: OS Independent
Classifier: Programming Language :: Python :: 3
Classifier: Programming Language :: Python :: 3.7
Classifier: Programming Language :: Python :: 3.8
Classifier: Programming Language :: Python :: 3.9
Classifier: Programming Language :: Python :: 3.10
Classifier: Programming Language :: Python :: 3.11
Requires-Python: >=3.7
License-File: LICENSE
Dynamic: author
Dynamic: home-page
Dynamic: license-file
Dynamic: requires-python
